hypergrad/__about__.py
hypergrad/__init__.py
hypergrad/approx_hypergrad.py
hypergrad/optimizers.py
hypergrad/solver.py
hypergrad/utils.py
hypergrad-0.0.1.dist-info/METADATA
hypergrad-0.0.1.dist-info/WHEEL
hypergrad-0.0.1.dist-info/licenses/LICENSE.txt
hypergrad-0.0.1.dist-info/RECORD
