Metadata-Version: 2.1
Name: hypergrad
Version: 0.0.1
Summary: Simple and extensible hypergradient for PyTorch
Project-URL: Documentation, https://github.com/moskomule/hypergrad
Project-URL: Issues, https://github.com/moskomule/hypergrad/issues
Project-URL: Source, https://github.com/moskomule/hypergrad
Author-email: Ryuichiro Hataya <hataya@nlab.ci.i.u-tokyo.ac.jp>
License-Expression: MIT
License-File: LICENSE.txt
Classifier: Development Status :: 4 - Beta
Classifier: Programming Language :: Python
Classifier: Programming Language :: Python :: 3.10
Classifier: Programming Language :: Python :: 3.11
Classifier: Programming Language :: Python :: Implementation :: CPython
Requires-Python: >=3.10
Requires-Dist: rich
Requires-Dist: torch
Requires-Dist: torchvision
